piqa/__init__.py
piqa/fid.py
piqa/fsim.py
piqa/gmsd.py
piqa/haarpsi.py
piqa/lpips.py
piqa/mdsi.py
piqa/psnr.py
piqa/ssim.py
piqa/tv.py
piqa/vsi.py
piqa/utils/__init__.py
piqa/utils/color.py
piqa/utils/functional.py
piqa-1.3.2.dist-info/LICENSE
piqa-1.3.2.dist-info/METADATA
piqa-1.3.2.dist-info/WHEEL
piqa-1.3.2.dist-info/top_level.txt
piqa-1.3.2.dist-info/RECORD
