Metadata-Version: 2.1
Name: piqa
Version: 1.3.2
Summary: PyTorch Image Quality Assessment
Author: François Rozet
Author-email: francois.rozet@outlook.com
Project-URL: Documentation, https://piqa.readthedocs.io
Project-URL: Source, https://github.com/francois-rozet/piqa
Project-URL: Tracker, https://github.com/francois-rozet/piqa/issues
Keywords: torch,vision,image,quality,metrics
Classifier: Intended Audience :: Developers
Classifier: Intended Audience :: Science/Research
Classifier: Natural Language :: English
Classifier: Operating System :: OS Independent
Classifier: Programming Language :: Python :: 3
Requires-Python: >=3.8
License-File: LICENSE
Requires-Dist: torch >=1.12.0
Requires-Dist: torchvision >=0.13.0
